{
  "version": "2.127.1-0",
  "grid": {
    "layers": {
      "Default layer": {
        "name": "Default layer"
      }
    },
    "xWidth": 10,
    "yHeight": 10
  },
  "modules": [
    {
      "url": "modules/types/client_interaction/code_editor/",
      "configuration": {
        "sections": {},
        "groups": {
          "group": [
            {
              "mode": ["html"],
              "outputType": [null],
              "btnvalue": ["Send script"],
              "iseditable": [["editable"]],
              "hasButton": [["button"]],
              "variable": [[]],
              "storeOnChange": [["store"]],
              "debouncing": [250],
              "script": [
                "Title: <input name=\"title\"><br> \n\n<select name=\"kind\">\n    <option value=\"\"> -- select an option -- </option>\n    <option value=\"A\">A</option>\n    <option value=\"B\">B</option>\n</select>\n"
              ]
            }
          ],
          "ace": [
            {
              "useSoftTabs": [["yes"]],
              "tabSize": [4]
            }
          ]
        }
      },
      "layers": {
        "Default layer": {
          "position": {
            "left": 0,
            "top": 0
          },
          "size": {
            "width": 47,
            "height": 32
          },
          "zIndex": 0,
          "display": true,
          "title": "",
          "bgColor": [255, 255, 255, 0],
          "wrapper": true,
          "created": true,
          "name": "Default layer"
        }
      },
      "id": 1,
      "vars_in": [{}],
      "actions_in": [{}],
      "vars_out": [
        {
          "event": "onEditorChange",
          "rel": "data",
          "jpath": [],
          "name": "template"
        }
      ],
      "actions_out": [
        {
          "jpath": []
        }
      ],
      "toolbar": {
        "custom": [
          [
            {
              "title": "",
              "icon": "",
              "action": "",
              "position": "begin",
              "color": [100, 100, 100, 1]
            }
          ]
        ],
        "common": [
          {
            "toolbar": [["Open Preferences"]]
          }
        ]
      },
      "css": [
        {
          "fontSize": [""],
          "fontFamily": [""]
        }
      ],
      "title": ""
    },
    {
      "url": "modules/types/edition/object_editor/",
      "configuration": {
        "sections": {},
        "groups": {
          "group": [
            {
              "editable": ["text"],
              "expanded": [[]],
              "storeObject": [["expand"]],
              "displayValue": [[]],
              "searchBox": [["search"]],
              "sendButton": [["send"]],
              "output": ["new"],
              "storedObject": ["{\"title\":\"abfddc\",\"kind\":\"A\"}"]
            }
          ]
        }
      },
      "layers": {
        "Default layer": {
          "position": {
            "left": 89,
            "top": 0
          },
          "size": {
            "width": 49,
            "height": 32
          },
          "zIndex": 0,
          "display": true,
          "title": "Input",
          "bgColor": [255, 255, 255, 0],
          "wrapper": true,
          "created": true,
          "name": "Default layer"
        }
      },
      "id": 2,
      "vars_in": [{}],
      "actions_in": [{}],
      "vars_out": [
        {
          "event": "onObjectChange",
          "rel": "output",
          "jpath": [],
          "name": "data"
        }
      ],
      "actions_out": [
        {
          "jpath": []
        }
      ],
      "toolbar": {
        "custom": [
          [
            {
              "title": "",
              "icon": "",
              "action": "",
              "position": "begin",
              "color": [100, 100, 100, 1]
            }
          ]
        ],
        "common": [
          {
            "toolbar": [["Open Preferences"]]
          }
        ]
      },
      "css": [
        {
          "fontSize": [""],
          "fontFamily": [""]
        }
      ],
      "title": "Input"
    },
    {
      "url": "modules/types/display/template-twig/",
      "configuration": {
        "sections": {},
        "groups": {
          "group": [
            {
              "selectable": [[]],
              "template": [""],
              "modifyInForm": [["yes"]],
              "debouncing": [100],
              "formOptions": [[]]
            }
          ]
        }
      },
      "layers": {
        "Default layer": {
          "position": {
            "left": 48,
            "top": 0
          },
          "size": {
            "width": 40,
            "height": 26
          },
          "zIndex": 0,
          "display": true,
          "title": "",
          "bgColor": [255, 255, 255, 0],
          "wrapper": true,
          "created": true,
          "name": "Default layer"
        }
      },
      "id": 3,
      "vars_in": [
        {
          "rel": "tpl",
          "name": "template"
        },
        {
          "rel": "form",
          "name": "data"
        }
      ],
      "actions_in": [{}],
      "vars_out": [
        {
          "jpath": []
        }
      ],
      "actions_out": [
        {
          "jpath": []
        }
      ],
      "toolbar": {
        "custom": [
          [
            {
              "title": "",
              "icon": "",
              "action": "",
              "position": "begin",
              "color": [100, 100, 100, 1]
            }
          ]
        ],
        "common": [
          {
            "toolbar": [["Open Preferences"]]
          }
        ]
      },
      "css": [
        {
          "fontSize": [""],
          "fontFamily": [""]
        }
      ],
      "title": ""
    },
    {
      "url": "modules/types/edition/object_editor/",
      "configuration": {
        "sections": {},
        "groups": {
          "group": [
            {
              "editable": ["text"],
              "expanded": [[]],
              "storeObject": [["expand"]],
              "displayValue": [[]],
              "searchBox": [["search"]],
              "sendButton": [[]],
              "output": ["new"],
              "storedObject": ["{\"title\":\"abfddc\",\"kind\":\"\"}"]
            }
          ]
        }
      },
      "layers": {
        "Default layer": {
          "position": {
            "left": 89,
            "top": 33
          },
          "size": {
            "width": 49,
            "height": 32
          },
          "zIndex": 0,
          "display": true,
          "title": "Output",
          "bgColor": [255, 255, 255, 0],
          "wrapper": true,
          "created": true,
          "name": "Default layer"
        }
      },
      "id": 4,
      "vars_in": [
        {
          "rel": "value",
          "name": "data"
        }
      ],
      "actions_in": [{}],
      "vars_out": [
        {
          "jpath": []
        }
      ],
      "actions_out": [
        {
          "jpath": []
        }
      ],
      "toolbar": {
        "custom": [
          [
            {
              "title": "",
              "icon": "",
              "action": "",
              "position": "begin",
              "color": [100, 100, 100, 1]
            }
          ]
        ],
        "common": [
          {
            "toolbar": [["Open Preferences"]]
          }
        ]
      },
      "css": [
        {
          "fontSize": [""],
          "fontFamily": [""]
        }
      ],
      "title": "Output"
    },
    {
      "url": "modules/types/client_interaction/code_executor/",
      "configuration": {
        "sections": {},
        "groups": {
          "group": [
            {
              "display": [["editor", "buttons"]],
              "execOnLoad": [[]],
              "asyncAwait": [["top"]],
              "script": ["API.createData('data', undefined);"]
            }
          ],
          "libs": [[{}]],
          "buttons": [
            [
              {
                "name": "button1",
                "label": "Execute",
                "hide": [],
                "disable": []
              }
            ]
          ]
        }
      },
      "layers": {
        "Default layer": {
          "position": {
            "left": 48,
            "top": 27
          },
          "size": {
            "width": 40,
            "height": 27
          },
          "zIndex": 0,
          "display": true,
          "title": "",
          "bgColor": [255, 255, 255, 0],
          "wrapper": true,
          "created": true,
          "name": "Default layer"
        }
      },
      "id": 5,
      "vars_in": [{}],
      "actions_in": [{}],
      "vars_out": [
        {
          "jpath": []
        }
      ],
      "actions_out": [
        {
          "jpath": []
        }
      ],
      "toolbar": {
        "custom": [
          [
            {
              "title": "",
              "icon": "",
              "action": "",
              "position": "begin",
              "color": [100, 100, 100, 1]
            }
          ]
        ],
        "common": [
          {
            "toolbar": [["Open Preferences"]]
          }
        ]
      },
      "css": [
        {
          "fontSize": [""],
          "fontFamily": [""]
        }
      ],
      "title": ""
    },
    {
      "url": "modules/types/client_interaction/code_executor/",
      "configuration": {
        "sections": {},
        "groups": {
          "group": [
            {
              "display": [["editor", "buttons"]],
              "execOnLoad": [[]],
              "asyncAwait": [["top"]],
              "script": [
                "const data = API.getData('data');\ndata.kind= \"\";\ndata.triggerChange();"
              ]
            }
          ],
          "libs": [[{}]],
          "buttons": [
            [
              {
                "name": "button1",
                "label": "Execute",
                "hide": [],
                "disable": []
              }
            ]
          ]
        }
      },
      "layers": {
        "Default layer": {
          "position": {
            "left": 4,
            "top": 35
          },
          "size": {
            "width": 40,
            "height": 27
          },
          "zIndex": 0,
          "display": true,
          "title": "",
          "bgColor": [255, 255, 255, 0],
          "wrapper": true,
          "created": true,
          "name": "Default layer"
        }
      },
      "id": 6,
      "vars_in": [{}],
      "actions_in": [{}],
      "vars_out": [
        {
          "jpath": []
        }
      ],
      "actions_out": [
        {
          "jpath": []
        }
      ],
      "toolbar": {
        "custom": [
          [
            {
              "title": "",
              "icon": "",
              "action": "",
              "position": "begin",
              "color": [100, 100, 100, 1]
            }
          ]
        ],
        "common": [
          {
            "toolbar": [["Open Preferences"]]
          }
        ]
      },
      "css": [
        {
          "fontSize": [""],
          "fontFamily": [""]
        }
      ],
      "title": ""
    }
  ],
  "variables": [
    {
      "jpath": [""]
    }
  ],
  "aliases": [
    {
      "path": "https://www.lactame.com/github/cheminfo-js/visualizer-helper/fede69d611616d26d5f70a4fc053eceac6612b68",
      "alias": "vh"
    },
    {
      "path": "http://localhost:9898/cheminfo-js/visualizer-helper",
      "alias": "vhxx"
    }
  ],
  "configuration": {
    "title": "Twig dynamic form experiments"
  },
  "actionscripts": [
    {
      "sections": {},
      "groups": {
        "action": [
          {
            "name": [null],
            "script": [null]
          }
        ]
      }
    }
  ],
  "init_script": [
    {
      "sections": {},
      "groups": {
        "general": [
          {
            "script": ["API.createData('data', {});\n"]
          }
        ]
      }
    }
  ],
  "custom_filters": [
    {
      "sections": {
        "modules": [
          {
            "sections": {},
            "groups": {
              "modules": [[{}]]
            }
          }
        ],
        "filtersLib": [
          {
            "sections": {},
            "groups": {
              "filters": [[{}]]
            }
          }
        ],
        "filters": [
          {
            "sections": {},
            "groups": {
              "filter": [
                {
                  "name": [null],
                  "script": [null]
                }
              ],
              "libs": [[{}]]
            }
          }
        ]
      },
      "groups": {}
    }
  ],
  "actionfiles": [
    {
      "sections": {},
      "groups": {
        "action": [[{}]]
      }
    }
  ]
}
