{
  "name": "setImmediate polyfill",
  "main": "setimmediate.js",
  "version": "1.0.0",
  "homepage": "https://github.com/Octane/setImmediate",
  "authors": [
    "Dmitry Korobkin <dmitry.korobkin@gmail.com>"
  ],
  "description": "setImmediate polyfill",
  "keywords": [
    "setImmediate",
    "clearImmediate",
    "polyfill",
    "client",
    "browser"
  ],
  "license": "MIT",
  "ignore": [
    ".gitignore",
    "bower.json",
    "index.html",
    "LICENSE"
  ],
  "_release": "1.0.0",
  "_resolution": {
    "type": "version",
    "tag": "v1.0.0",
    "commit": "2d5fedb1ff7097e7a7c7eb150fca38d812031eff"
  },
  "_source": "git://github.com/Octane/setImmediate.git",
  "_target": "*",
  "_originalSource": "setImmediate"
}